gkms/__init__.py
gkms/cli.py
gkms/utils.py
gkms/cmd/__init__.py
gkms/cmd/decrypt.py
gkms/cmd/encrypt.py
gkms/cmd/reencrypt.py
gkms-0.0.1.dist-info/LICENSE
gkms-0.0.1.dist-info/METADATA
gkms-0.0.1.dist-info/WHEEL
gkms-0.0.1.dist-info/entry_points.txt
gkms-0.0.1.dist-info/top_level.txt
gkms-0.0.1.dist-info/RECORD
