Metadata-Version: 2.1
Name: gkms
Version: 0.0.1
Summary: A simple utility for using GCP Cloud KMS to encrypt and decrypt secrets and storing them in GCS.
Home-page: https://github.com/getsentry/gkms
Author: zylphrex
Author-email: zylphrex@gmail.com
Maintainer: zylphrex
Maintainer-email: zylphrex@gmail.com
License: UNKNOWN
Keywords: cloudgcp,gcs,google,google-cloud-kms,google-cloud-storage,kms,encrypt,decrypt
Platform: Posix; MacOS X; Windows
Classifier: Development Status :: 3 - Alpha
Classifier: Environment :: Console
Classifier: Intended Audience :: Developers
Classifier: License :: OSI Approved :: Apache Software License
Classifier: Programming Language :: Python :: 3 :: Only
Classifier: Topic :: Security
Requires-Dist: google-cloud-storage (<2,>=1.16.1)
Requires-Dist: google-cloud-kms (<2,>=1.1.0)
Provides-Extra: dev
Requires-Dist: pytest (<6,>=5.0.1) ; extra == 'dev'
